COPYING
MANIFEST.in
README.rst
setup.py
collapse_whitespace_templatetag/__init__.py
collapse_whitespace_templatetag/models.py
collapse_whitespace_templatetag/templatetags/__init__.py
collapse_whitespace_templatetag/templatetags/collapse_whitespace.py
django_collapse_whitespace_templatetag.egg-info/PKG-INFO
django_collapse_whitespace_templatetag.egg-info/SOURCES.txt
django_collapse_whitespace_templatetag.egg-info/dependency_links.txt
django_collapse_whitespace_templatetag.egg-info/requires.txt
django_collapse_whitespace_templatetag.egg-info/top_level.txt