Metadata-Version: 1.0
Name: django-collapse-whitespace-templatetag
Version: 1.0.2
Summary: Simple template tag for Django to collapse whitespace
Home-page: https://chris-lamb.co.uk/projects/django-collapse-whitespace-templatetag
Author: Chris Lamb
Author-email: chris@chris-lamb.co.uk
License: BSD
Platform: UNKNOWN
